{
  "models": {
    "Ûthar the Destined": {
      "name": "Ûthar the Destined",
      "unitImage": "",
      "stats": {
        "M": "5\"",
        "T": "5",
        "SV": "3+",
        "W": "5",
        "LD": "7+",
        "OC": "1"
      },
      "meleeWeapons": [],
      "rangedWeapons": []
    },
    "Kâhl": {
      "name": "Kâhl",
      "unitImage": "",
      "stats": {
        "M": "5\"",
        "T": "5",
        "SV": "3+",
        "W": "4",
        "LD": "7+",
        "OC": "1"
      },
      "meleeWeapons": [],
      "rangedWeapons": []
    },
    "Einhyr Champion": {
      "name": "Einhyr Champion",
      "unitImage": "",
      "stats": {
        "M": "5\"",
        "T": "6",
        "SV": "2+",
        "W": "5",
        "LD": "7+",
        "OC": "1"
      },
      "meleeWeapons": [],
      "rangedWeapons": []
    },
    "Sagitaur": {
      "name": "Sagitaur",
      "unitImage": "",
      "stats": {
        "M": "12\"",
        "T": "10",
        "SV": "3+",
        "W": "9",
        "LD": "7+",
        "OC": "3"
      },
      "meleeWeapons": [],
      "rangedWeapons": []
    },
    "Hekaton Land Fortress": {
      "name": "Hekaton Land Fortress",
      "unitImage": "",
      "stats": {
        "M": "10\"",
        "T": "12",
        "SV": "2+",
        "W": "16",
        "LD": "7+",
        "OC": "5"
      },
      "meleeWeapons": [],
      "rangedWeapons": []
    }
  },
  "upgrades": {
    "Detachment Choice": "Detachment Choice",
    "Rampart crest": "Rampart crest",
    "Autoch-pattern combi-bolter": "Autoch-pattern combi-bolter",
    "Volkanite disintegrator": "Volkanite disintegrator",
    "Warlord": "Warlord",
    "Teleport crest": "Teleport crest",
    "Weavefield crest": "Weavefield crest",
    "Autoch-pattern bolter": "Autoch-pattern bolter",
    "Bolt revolver": "Bolt revolver",
    "Bolt shotgun": "Bolt shotgun",
    "Magna-coil autocannon": "Magna-coil autocannon",
    "Plasma knife": "Plasma knife",
    "Twin bolt cannon": "Twin bolt cannon",
    "MATR autocannon": "MATR autocannon"
  },
  "units": {
    "Hearthkyn Warriors": {
      "name": "Hearthkyn Warriors",
      "unitImage": "",
      "stats": {
        "M": "5\"",
        "T": "5",
        "SV": "4+",
        "W": "1",
        "LD": "7+",
        "OC": "2"
      },
      "meleeWeapons": [],
      "rangedWeapons": []
    },
    "Grimnyr": {
      "name": "Grimnyr",
      "unitImage": "",
      "stats": {},
      "meleeWeapons": [],
      "rangedWeapons": []
    },
    "Brôkhyr Iron-master": {
      "name": "Brôkhyr Iron-master",
      "unitImage": "",
      "stats": {},
      "meleeWeapons": [],
      "rangedWeapons": []
    },
    "Einhyr Hearthguard": {
      "name": "Einhyr Hearthguard",
      "unitImage": "",
      "stats": {},
      "meleeWeapons": [],
      "rangedWeapons": []
    },
    "Cthonian Beserks": {
      "name": "Cthonian Beserks",
      "unitImage": "",
      "stats": {},
      "meleeWeapons": [],
      "rangedWeapons": []
    },
    "Hernkyn Pioneers": {
      "name": "Hernkyn Pioneers",
      "unitImage": "",
      "stats": {
        "M": "12\"",
        "T": "6",
        "SV": "4+",
        "W": "3",
        "LD": "7+",
        "OC": "2"
      },
      "meleeWeapons": [],
      "rangedWeapons": []
    },
    "Brôkhyr Thunderkyn": {
      "name": "Brôkhyr Thunderkyn",
      "unitImage": "",
      "stats": {
        "M": "5\"",
        "T": "6",
        "SV": "3+",
        "W": "3",
        "LD": "7+",
        "OC": "1"
      },
      "meleeWeapons": [],
      "rangedWeapons": []
    },
    "Hernkyn Yaegirs": {
      "name": "Hernkyn Yaegirs",
      "unitImage": "",
      "stats": {
        "M": "6\"",
        "T": "5",
        "SV": "5+",
        "W": "1",
        "LD": "7+",
        "OC": "1"
      },
      "meleeWeapons": [],
      "rangedWeapons": []
    }
  }
}